CoolEIoT/__init__.py
CoolEIoT/main.py
cooleiot-0.0.7.dist-info/METADATA
cooleiot-0.0.7.dist-info/WHEEL
cooleiot-0.0.7.dist-info/top_level.txt
cooleiot-0.0.7.dist-info/RECORD
